cc_feishu/__init__.py
cc_feishu/client.py
cc_feishu/endpoints.py
cc_feishu/errors.py
cc_feishu/helpers.py
cc_feishu/typing.py
cc_feishu-0.1.4.dist-info/LICENSE
cc_feishu-0.1.4.dist-info/METADATA
cc_feishu-0.1.4.dist-info/WHEEL
cc_feishu-0.1.4.dist-info/top_level.txt
cc_feishu-0.1.4.dist-info/RECORD
