Metadata-Version: 2.1
Name: cc-feishu
Version: 0.1.4
Summary: my feishu package
Home-page: https://github.com/houm01/cc-feishu
License-File: LICENSE
